transforms/__init__.py
transforms/preprocessing_functions_for_cv2.py
transforms/transforms_for_cv2.py
transforms_for_ndarray-0.0.4.dist-info/LICENSE
transforms_for_ndarray-0.0.4.dist-info/METADATA
transforms_for_ndarray-0.0.4.dist-info/WHEEL
transforms_for_ndarray-0.0.4.dist-info/top_level.txt
transforms_for_ndarray-0.0.4.dist-info/RECORD
